<?xml version="1.0" encoding="utf-8" ?><dwsync><file name="ImgResponsive_Placeholder.png" server="192.168.0.124//var/www/html/" local="3612305880" remote="3619344140" Dst="-1" /><file name="404.jpeg" server="192.168.0.124//var/www/html/" local="3614691601" remote="3619344142" Dst="-1" /><file name="debianpowered_longways.png" server="192.168.0.124//var/www/html/" local="3614688125" remote="3619344141" Dst="-1" /><file name="RPi-Logo-Landscape-Reg-SCREEN.png" server="192.168.0.124//var/www/html/" local="3614687587" remote="3619344140" Dst="-1" /><file name="The_Scratch_Logo.png" server="192.168.0.124//var/www/html/" local="3604140580" remote="3619344125" Dst="-1" /><file name="trinketlogo.png" server="192.168.0.124//var/www/html/" local="3615810318" remote="3619344125" Dst="-1" /><file name="deadmac.jpg" server="192.168.0.124//var/www/html/" local="3615902680" remote="3620935928" Dst="-1" /><file name="mindstorms.png" server="192.168.0.124//var/www/html/" local="3616073136" remote="3619344140" Dst="-1" /><file name="w3c.png" server="192.168.0.124//var/www/html/" local="3616073196" remote="3619344125" Dst="-1" /><file name="bootstrap-solid.svg" server="192.168.0.124//var/www/html/" local="3616162027" remote="3619344142" Dst="-1" /><file name="icepoo.jpeg" server="192.168.0.124//var/www/html/" local="3619288673" remote="3619344155" Dst="-1" /><file name="SORRY_Vector_Letters_icon.png" server="192.168.0.124//var/www/html/" local="3617363379" remote="3620935928" Dst="-1" /><file name="we'llberightback.png" server="192.168.0.124//var/www/html/" local="3617722175" remote="3619344125" Dst="-1" /><file name="bsod.jpg" server="192.168.0.124//var/www/html/" local="3616338109" remote="3619344142" Dst="-1" /><file name="ny.png" server="192.168.0.124//var/www/html/" local="3616615742" remote="3619269168" Dst="-1" /><file name=".DS_Store" server="192.168.0.124//var/www/html/" local="3619458168" remote="3619462045" Dst="-1" /><file name="codelogo.png" server="192.168.0.124//var/www/html/" local="3619791941" remote="3619792503" Dst="-1" /><file name="rpi3.png" server="192.168.0.124//var/www/html/" local="3619344140" remote="3619344140" Dst="-1" /><file name="we'llberightback.png" server="osx/Applications/MAMP/htdocs/" local="3617722175" remote="3617722175" Dst="-1" /><file name="w3c.png" server="osx/Applications/MAMP/htdocs/" local="3616073196" remote="3616073196" Dst="-1" /><file name="trinketlogo.png" server="osx/Applications/MAMP/htdocs/" local="3615810318" remote="3615810318" Dst="-1" /><file name="The_Scratch_Logo.png" server="osx/Applications/MAMP/htdocs/" local="3604140580" remote="3604140580" Dst="-1" /><file name="SORRY_Vector_Letters_icon.png" server="osx/Applications/MAMP/htdocs/" local="3617363379" remote="3617363379" Dst="-1" /><file name="rpi3.png" server="osx/Applications/MAMP/htdocs/" local="3619344140" remote="3619344140" Dst="-1" /><file name="RPi-Logo-Landscape-Reg-SCREEN.png" server="osx/Applications/MAMP/htdocs/" local="3614687587" remote="3614687587" Dst="-1" /><file name="ny.png" server="osx/Applications/MAMP/htdocs/" local="3616615742" remote="3616615742" Dst="-1" /><file name="mindstorms.png" server="osx/Applications/MAMP/htdocs/" local="3616073136" remote="3616073136" Dst="-1" /><file name="ImgResponsive_Placeholder.png" server="osx/Applications/MAMP/htdocs/" local="3612305880" remote="3612305880" Dst="-1" /><file name="icepoo.jpeg" server="osx/Applications/MAMP/htdocs/" local="3619288673" remote="3619288673" Dst="-1" /><file name="debianpowered_longways.png" server="osx/Applications/MAMP/htdocs/" local="3614688125" remote="3614688125" Dst="-1" /><file name="deadmac.jpg" server="osx/Applications/MAMP/htdocs/" local="3615902680" remote="3615902680" Dst="-1" /><file name="codelogo.png" server="osx/Applications/MAMP/htdocs/" local="3619791941" remote="3619791941" Dst="-1" /><file name="bsod.jpg" server="osx/Applications/MAMP/htdocs/" local="3616338109" remote="3616338109" Dst="-1" /><file name="bootstrap-solid.svg" server="osx/Applications/MAMP/htdocs/" local="3616162027" remote="3616162027" Dst="-1" /><file name="404.jpeg" server="osx/Applications/MAMP/htdocs/" local="3614691601" remote="3614691601" Dst="-1" /><file name=".DS_Store" server="osx/Applications/MAMP/htdocs/" local="3619796771" remote="3619796771" Dst="-1" /><file name="StickLifeMiniRedo1.bmp" server="192.168.0.124//var/www/html/" local="3620583990" remote="3621624277" Dst="-1" /><file name="googlelogo.png" server="192.168.0.124//var/www/html/" local="3621189550" remote="3621624277" Dst="-1" /><file name="ev3.jpeg" server="192.168.0.124//var/www/html/" local="3619344141" remote="3619344141" Dst="-1" /><file name="falogo.png" server="192.168.0.124//var/www/html/" local="3622214237" remote="3622217357" Dst="-1" /><file name="clippy.gif" server="192.168.4.124//var/www/html/" local="3627226401" remote="3627229220" Dst="-1" /><file name="clippy.jpg" server="192.168.4.124//var/www/html/" local="3627226401" remote="3627229220" Dst="-1" /><file name="nuggetbravedown.jpeg" server="192.168.4.124//var/www/html/" local="3627226401" remote="3627229221" Dst="-1" /><file name="homepage.png" server="192.168.4.124//var/www/html/" local="3627310404" remote="3627312436" Dst="-1" /><file name="404.jpeg" server="192.168.4.124//var/www/html/" local="3627226401" remote="3627229220" Dst="-1" /><file name="bootstrap-solid.svg" server="192.168.4.124//var/www/html/" local="3627226401" remote="3627229220" Dst="-1" /><file name="bsod.jpg" server="192.168.4.124//var/www/html/" local="3627226401" remote="3627229220" Dst="-1" /><file name="codelogo.png" server="192.168.4.124//var/www/html/" local="3627310396" remote="3627312436" Dst="-1" /><file name="deadmac.jpg" server="192.168.4.124//var/www/html/" local="3627226401" remote="3627229220" Dst="-1" /><file name="debianpowered_longways.png" server="192.168.4.124//var/www/html/" local="3627310334" remote="3627312436" Dst="-1" /><file name="ev3.jpeg" server="192.168.4.124//var/www/html/" local="3627226401" remote="3627229220" Dst="-1" /><file name="falogo.png" server="192.168.4.124//var/www/html/" local="3627226401" remote="3627229221" Dst="-1" /><file name="googlelogo.png" server="192.168.4.124//var/www/html/" local="3627310601" remote="3627312436" Dst="-1" /><file name="icepoo.jpeg" server="192.168.4.124//var/www/html/" local="3627226401" remote="3627229221" Dst="-1" /><file name="ImgResponsive_Placeholder.png" server="192.168.4.124//var/www/html/" local="3627310330" remote="3627312436" Dst="-1" /><file name="mindstorms.png" server="192.168.4.124//var/www/html/" local="3627310732" remote="3627312436" Dst="-1" /><file name="ny.png" server="192.168.4.124//var/www/html/" local="3627310589" remote="3627312437" Dst="-1" /><file name="RPi-Logo-Landscape-Reg-SCREEN.png" server="192.168.4.124//var/www/html/" local="3627310579" remote="3627312437" Dst="-1" /><file name="rpi3.png" server="192.168.4.124//var/www/html/" local="3627310372" remote="3627312437" Dst="-1" /><file name="SORRY_Vector_Letters_icon.png" server="192.168.4.124//var/www/html/" local="3627310380" remote="3627312437" Dst="-1" /><file name="StickLifeMiniRedo1.bmp" server="192.168.4.124//var/www/html/" local="3627226401" remote="3627229224" Dst="-1" /><file name="The_Scratch_Logo.png" server="192.168.4.124//var/www/html/" local="3627310719" remote="3627312437" Dst="-1" /><file name="trinketlogo.png" server="192.168.4.124//var/www/html/" local="3627310589" remote="3627312437" Dst="-1" /><file name="w3c.png" server="192.168.4.124//var/www/html/" local="3627310630" remote="3627312437" Dst="-1" /><file name="we'llberightback.png" server="192.168.4.124//var/www/html/" local="3627310401" remote="3627312437" Dst="-1" /><file name="falogo-crunch.png" server="192.168.4.124//var/www/html/" local="3627310713" remote="3627312436" Dst="-1" /></dwsync>